{"cameraMode":{"drawMode":0,"name":"Shaded","section":"Shading Mode"},"sceneLighting":true,"audioPlay":false,"sceneViewState":{"m_AlwaysRefresh":false,"showFog":true,"showSkybox":true,"showFlares":true,"showImageEffects":true,"showParticleSystems":true,"showVisualEffectGraphs":true,"m_FxEnabled":true},"in2DMode":false,"pivot":{"x":56.65671920776367,"y":102.53752899169922,"z":148.0301055908203},"rotation":{"x":-0.04810361564159393,"y":-0.9409076571464539,"z":0.2991366386413574,"w":-0.15149690210819245},"size":17.24028778076172,"orthographic":false}